rpi_control_center/GPIO_engine.py
rpi_control_center/__init__.py
rpi_control_center/controls.py
rpi_control_center/data.py
rpi_control_center/rpi_usb.py
rpi_sensor_monitors/__init__.py
rpi_sensor_monitors/monitors.py
rpi_sensor_monitors/gravity/DFRobot_BME280.py
rpi_sensor_monitors/gravity/DFRobot_BME680.py
rpi_sensor_monitors/gravity/__init__.py
RPI_control_center-0.2.3.2.dist-info/LICENSE
RPI_control_center-0.2.3.2.dist-info/METADATA
RPI_control_center-0.2.3.2.dist-info/WHEEL
RPI_control_center-0.2.3.2.dist-info/top_level.txt
RPI_control_center-0.2.3.2.dist-info/RECORD
